niaarm/__init__.py
niaarm/__main__.py
niaarm/cli.py
niaarm/dataset.py
niaarm/feature.py
niaarm/mine.py
niaarm/niaarm.py
niaarm/preprocessing.py
niaarm/rule.py
niaarm/rule_list.py
niaarm/text.py
niaarm/visualize.py
niaarm-0.4.6.dist-info/WHEEL
niaarm-0.4.6.dist-info/entry_points.txt
niaarm-0.4.6.dist-info/METADATA
niaarm-0.4.6.dist-info/RECORD
