Metadata-Version: 2.4
Name: niaarm
Version: 0.4.6
Summary: A minimalistic framework for numerical association rule mining
Keywords: association rule mining,data science,numerical association rule mining,preprocessing,visualization
Author: Žiga Stupan, Iztok Fister Jr.
Author-email: Žiga Stupan <ziga.stupan1@student.um.si>, Iztok Fister Jr. <iztok@iztok-jr-fister.eu>
License-Expression: MIT
Requires-Dist: niapy>=2.6.1
Requires-Dist: numpy>=2.3.5
Requires-Dist: pandas>=2.3.3
Requires-Dist: nltk>=3.9.2
Requires-Dist: plotly>=6.5.0
Requires-Dist: scikit-learn>=1.8.0
Requires-Python: >=3.11
Project-URL: Documentation, https://niaarm.readthedocs.io/en/latest/
Project-URL: Homepage, https://github.com/firefly-cpp/NiaARM
Project-URL: Repository, https://github.com/firefly-cpp/NiaARM
